neo_utils-0.1.5.dist-info/DESCRIPTION.rst
neo_utils-0.1.5.dist-info/METADATA
neo_utils-0.1.5.dist-info/RECORD
neo_utils-0.1.5.dist-info/WHEEL
neo_utils-0.1.5.dist-info/metadata.json
neo_utils-0.1.5.dist-info/top_level.txt
neoutils/__init__.py
