Metadata-Version: 2.0
Name: neo-utils
Version: 0.1.5
Summary: Utilities for neo.
Home-page: https://github.com/deone/neo-utils
Author: Dayo Osikoya
Author-email: alwaysdeone@gmail.com
License: MIT
Keywords: ussd http session json response django
Platform: UNKNOWN
Classifier: Development Status :: 5 - Production/Stable
Classifier: Intended Audience :: Developers
Classifier: Topic :: Software Development :: Build Tools
Classifier: License :: OSI Approved :: MIT License
Classifier: Programming Language :: Python :: 2
Classifier: Programming Language :: Python :: 2.6
Classifier: Programming Language :: Python :: 2.7
Requires-Dist: Django (==1.11.10)
Requires-Dist: requests
